<?xml version="1.0" encoding="UTF-8" standalone="yes"?>
<unit xmlns="http://www.srcML.org/srcML/src" xmlns:pos="http://www.srcML.org/srcML/position" revision="1.0.0" language="Java" filename="src/UAVModeChangeMessage.java" pos:tabs="8"><package pos:start="1:1" pos:end="1:53">package <name pos:start="1:9" pos:end="1:52"><name pos:start="1:9" pos:end="1:11">edu</name><operator pos:start="1:12" pos:end="1:12">.</operator><name pos:start="1:13" pos:end="1:14">nd</name><operator pos:start="1:15" pos:end="1:15">.</operator><name pos:start="1:16" pos:end="1:24">dronology</name><operator pos:start="1:25" pos:end="1:25">.</operator><name pos:start="1:26" pos:end="1:33">gstation</name><operator pos:start="1:34" pos:end="1:34">.</operator><name pos:start="1:35" pos:end="1:43">connector</name><operator pos:start="1:44" pos:end="1:44">.</operator><name pos:start="1:45" pos:end="1:52">messages</name></name>;</package>

<import pos:start="3:1" pos:end="3:28">import <name pos:start="3:8" pos:end="3:27"><name pos:start="3:8" pos:end="3:11">java</name><operator pos:start="3:12" pos:end="3:12">.</operator><name pos:start="3:13" pos:end="3:14">io</name><operator pos:start="3:15" pos:end="3:15">.</operator><name pos:start="3:16" pos:end="3:27">Serializable</name></name>;</import>

<comment type="block" format="javadoc" pos:start="5:1" pos:end="10:3">/**
 * Monitoring message received from the GCS for a specific UAV.
 * 
 * @author Michael Vierhauser
 *
 */</comment>
<class pos:start="11:1" pos:end="35:1"><specifier pos:start="11:1" pos:end="11:6">public</specifier> class <name pos:start="11:14" pos:end="11:33">UAVModeChangeMessage</name> <super_list pos:start="11:35" pos:end="11:92"><extends pos:start="11:35" pos:end="11:68">extends <super pos:start="11:43" pos:end="11:68"><name pos:start="11:43" pos:end="11:68"><name pos:start="11:43" pos:end="11:60">AbstractUAVMessage</name><argument_list type="generic" pos:start="11:61" pos:end="11:68">&lt;<argument pos:start="11:62" pos:end="11:67"><name pos:start="11:62" pos:end="11:67">Object</name></argument>&gt;</argument_list></name></super></extends> <implements pos:start="11:70" pos:end="11:92">implements <super pos:start="11:81" pos:end="11:92"><name pos:start="11:81" pos:end="11:92">Serializable</name></super></implements></super_list> <block pos:start="11:94" pos:end="35:1">{

	<decl_stmt pos:start="13:9" pos:end="13:74"><decl pos:start="13:9" pos:end="13:73"><type pos:start="13:9" pos:end="13:33"><specifier pos:start="13:9" pos:end="13:15">private</specifier> <specifier pos:start="13:17" pos:end="13:22">static</specifier> <specifier pos:start="13:24" pos:end="13:28">final</specifier> <name pos:start="13:30" pos:end="13:33">long</name></type> <name pos:start="13:35" pos:end="13:50">serialVersionUID</name> <init pos:start="13:52" pos:end="13:73">= <expr pos:start="13:54" pos:end="13:73"><literal type="number" pos:start="13:54" pos:end="13:73">1502042637906425729L</literal></expr></init></decl>;</decl_stmt>
	<decl_stmt pos:start="14:9" pos:end="14:63"><decl pos:start="14:9" pos:end="14:62"><type pos:start="14:9" pos:end="14:34"><specifier pos:start="14:9" pos:end="14:14">public</specifier> <specifier pos:start="14:16" pos:end="14:21">static</specifier> <specifier pos:start="14:23" pos:end="14:27">final</specifier> <name pos:start="14:29" pos:end="14:34">String</name></type> <name pos:start="14:36" pos:end="14:47">MESSAGE_TYPE</name> <init pos:start="14:49" pos:end="14:62">= <expr pos:start="14:51" pos:end="14:62"><literal type="string" pos:start="14:51" pos:end="14:62">"modechange"</literal></expr></init></decl>;</decl_stmt>
	<decl_stmt pos:start="15:9" pos:end="15:49"><decl pos:start="15:9" pos:end="15:48"><type pos:start="15:9" pos:end="15:34"><specifier pos:start="15:9" pos:end="15:14">public</specifier> <specifier pos:start="15:16" pos:end="15:21">static</specifier> <specifier pos:start="15:23" pos:end="15:27">final</specifier> <name pos:start="15:29" pos:end="15:34">String</name></type> <name pos:start="15:36" pos:end="15:39">DATA</name> <init pos:start="15:41" pos:end="15:48">= <expr pos:start="15:43" pos:end="15:48"><literal type="string" pos:start="15:43" pos:end="15:48">"data"</literal></expr></init></decl>;</decl_stmt>
	<decl_stmt pos:start="16:9" pos:end="16:59"><decl pos:start="16:9" pos:end="16:58"><type pos:start="16:9" pos:end="16:44"><specifier pos:start="16:9" pos:end="16:14">public</specifier> <specifier pos:start="16:16" pos:end="16:21">static</specifier> <specifier pos:start="16:23" pos:end="16:27">final</specifier> <specifier pos:start="16:29" pos:end="16:37">transient</specifier> <name pos:start="16:39" pos:end="16:44">String</name></type> <name pos:start="16:46" pos:end="16:49">MODE</name> <init pos:start="16:51" pos:end="16:58">= <expr pos:start="16:53" pos:end="16:58"><literal type="string" pos:start="16:53" pos:end="16:58">"mode"</literal></expr></init></decl>;</decl_stmt>
	<decl_stmt pos:start="17:9" pos:end="17:71"><decl pos:start="17:9" pos:end="17:70"><type pos:start="17:9" pos:end="17:44"><specifier pos:start="17:9" pos:end="17:14">public</specifier> <specifier pos:start="17:16" pos:end="17:21">static</specifier> <specifier pos:start="17:23" pos:end="17:27">final</specifier> <specifier pos:start="17:29" pos:end="17:37">transient</specifier> <name pos:start="17:39" pos:end="17:44">String</name></type> <name pos:start="17:46" pos:end="17:50">GS_ID</name> <init pos:start="17:52" pos:end="17:70">= <expr pos:start="17:54" pos:end="17:70"><literal type="string" pos:start="17:54" pos:end="17:70">"groundstationid"</literal></expr></init></decl>;</decl_stmt>
	<decl_stmt pos:start="18:9" pos:end="18:62"><decl pos:start="18:9" pos:end="18:61"><type pos:start="18:9" pos:end="18:44"><specifier pos:start="18:9" pos:end="18:14">public</specifier> <specifier pos:start="18:16" pos:end="18:21">static</specifier> <specifier pos:start="18:23" pos:end="18:27">final</specifier> <specifier pos:start="18:29" pos:end="18:37">transient</specifier> <name pos:start="18:39" pos:end="18:44">String</name></type> <name pos:start="18:46" pos:end="18:51">UAV_ID</name> <init pos:start="18:53" pos:end="18:61">= <expr pos:start="18:55" pos:end="18:61"><literal type="string" pos:start="18:55" pos:end="18:61">"uavid"</literal></expr></init></decl>;</decl_stmt>

	<constructor pos:start="20:9" pos:end="23:9"><specifier pos:start="20:9" pos:end="20:14">public</specifier> <name pos:start="20:16" pos:end="20:35">UAVModeChangeMessage</name><parameter_list pos:start="20:36" pos:end="20:86">(<parameter pos:start="20:37" pos:end="20:58"><decl pos:start="20:37" pos:end="20:58"><type pos:start="20:37" pos:end="20:58"><name pos:start="20:37" pos:end="20:42">String</name></type> <name pos:start="20:44" pos:end="20:58">groundstationid</name></decl></parameter>, <parameter pos:start="20:61" pos:end="20:72"><decl pos:start="20:61" pos:end="20:72"><type pos:start="20:61" pos:end="20:72"><name pos:start="20:61" pos:end="20:66">String</name></type> <name pos:start="20:68" pos:end="20:72">uavid</name></decl></parameter>, <parameter pos:start="20:75" pos:end="20:85"><decl pos:start="20:75" pos:end="20:85"><type pos:start="20:75" pos:end="20:85"><name pos:start="20:75" pos:end="20:80">String</name></type> <name pos:start="20:82" pos:end="20:85">mode</name></decl></parameter>)</parameter_list> <block pos:start="20:88" pos:end="23:9">{<block_content pos:start="21:17" pos:end="22:37">
		<expr_stmt pos:start="21:17" pos:end="21:60"><expr pos:start="21:17" pos:end="21:59"><call pos:start="21:17" pos:end="21:59"><name pos:start="21:17" pos:end="21:21">super</name><argument_list pos:start="21:22" pos:end="21:59">(<argument pos:start="21:23" pos:end="21:34"><expr pos:start="21:23" pos:end="21:34"><name pos:start="21:23" pos:end="21:34">MESSAGE_TYPE</name></expr></argument>, <argument pos:start="21:37" pos:end="21:51"><expr pos:start="21:37" pos:end="21:51"><name pos:start="21:37" pos:end="21:51">groundstationid</name></expr></argument>, <argument pos:start="21:54" pos:end="21:58"><expr pos:start="21:54" pos:end="21:58"><name pos:start="21:54" pos:end="21:58">uavid</name></expr></argument>)</argument_list></call></expr>;</expr_stmt>
		<expr_stmt pos:start="22:17" pos:end="22:37"><expr pos:start="22:17" pos:end="22:36"><call pos:start="22:17" pos:end="22:36"><name pos:start="22:17" pos:end="22:24"><name pos:start="22:17" pos:end="22:20">data</name><operator pos:start="22:21" pos:end="22:21">.</operator><name pos:start="22:22" pos:end="22:24">put</name></name><argument_list pos:start="22:25" pos:end="22:36">(<argument pos:start="22:26" pos:end="22:29"><expr pos:start="22:26" pos:end="22:29"><name pos:start="22:26" pos:end="22:29">MODE</name></expr></argument>, <argument pos:start="22:32" pos:end="22:35"><expr pos:start="22:32" pos:end="22:35"><name pos:start="22:32" pos:end="22:35">mode</name></expr></argument>)</argument_list></call></expr>;</expr_stmt>
	</block_content>}</block></constructor>

	<function pos:start="25:9" pos:end="29:9"><annotation pos:start="25:9" pos:end="25:17">@<name pos:start="25:10" pos:end="25:17">Override</name></annotation>
	<type pos:start="26:9" pos:end="26:19"><specifier pos:start="26:9" pos:end="26:14">public</specifier> <name pos:start="26:16" pos:end="26:19">void</name></type> <name pos:start="26:21" pos:end="26:27">setType</name><parameter_list pos:start="26:28" pos:end="26:40">(<parameter pos:start="26:29" pos:end="26:39"><decl pos:start="26:29" pos:end="26:39"><type pos:start="26:29" pos:end="26:34"><name pos:start="26:29" pos:end="26:34">String</name></type> <name pos:start="26:36" pos:end="26:39">type</name></decl></parameter>)</parameter_list> <block pos:start="26:42" pos:end="29:9">{<block_content pos:start="27:17" pos:end="27:33">
		<expr_stmt pos:start="27:17" pos:end="27:33"><expr pos:start="27:17" pos:end="27:32"><name pos:start="27:17" pos:end="27:25"><name pos:start="27:17" pos:end="27:20">this</name><operator pos:start="27:21" pos:end="27:21">.</operator><name pos:start="27:22" pos:end="27:25">type</name></name> <operator pos:start="27:27" pos:end="27:27">=</operator> <name pos:start="27:29" pos:end="27:32">type</name></expr>;</expr_stmt>

	</block_content>}</block></function>

	<function pos:start="31:9" pos:end="33:9"><type pos:start="31:9" pos:end="31:21"><specifier pos:start="31:9" pos:end="31:14">public</specifier> <name pos:start="31:16" pos:end="31:21">String</name></type> <name pos:start="31:23" pos:end="31:29">getMode</name><parameter_list pos:start="31:30" pos:end="31:31">()</parameter_list> <block pos:start="31:33" pos:end="33:9">{<block_content pos:start="32:17" pos:end="32:49">
		<return pos:start="32:17" pos:end="32:49">return <expr pos:start="32:24" pos:end="32:48"><call pos:start="32:24" pos:end="32:37"><name pos:start="32:24" pos:end="32:31"><name pos:start="32:24" pos:end="32:27">data</name><operator pos:start="32:28" pos:end="32:28">.</operator><name pos:start="32:29" pos:end="32:31">get</name></name><argument_list pos:start="32:32" pos:end="32:37">(<argument pos:start="32:33" pos:end="32:36"><expr pos:start="32:33" pos:end="32:36"><name pos:start="32:33" pos:end="32:36">MODE</name></expr></argument>)</argument_list></call><operator pos:start="32:38" pos:end="32:38">.</operator><call pos:start="32:39" pos:end="32:48"><name pos:start="32:39" pos:end="32:46">toString</name><argument_list pos:start="32:47" pos:end="32:48">()</argument_list></call></expr>;</return>
	</block_content>}</block></function>

}</block></class>
</unit>
