<?xml version="1.0" encoding="UTF-8" standalone="yes"?>
<unit xmlns="http://www.srcML.org/srcML/src" xmlns:pos="http://www.srcML.org/srcML/position" revision="1.0.0" language="Java" filename="flatCode/SetTargetAltitudeMessage.java" pos:tabs="8"><package pos:start="1:1" pos:end="1:67">package <name pos:start="1:9" pos:end="1:66"><name pos:start="1:9" pos:end="1:11">edu</name><operator pos:start="1:12" pos:end="1:12">.</operator><name pos:start="1:13" pos:end="1:14">nd</name><operator pos:start="1:15" pos:end="1:15">.</operator><name pos:start="1:16" pos:end="1:24">dronology</name><operator pos:start="1:25" pos:end="1:25">.</operator><name pos:start="1:26" pos:end="1:29">core</name><operator pos:start="1:30" pos:end="1:30">.</operator><name pos:start="1:31" pos:end="1:37">vehicle</name><operator pos:start="1:38" pos:end="1:38">.</operator><name pos:start="1:39" pos:end="1:58">manageddroneinternal</name><operator pos:start="1:59" pos:end="1:59">.</operator><name pos:start="1:60" pos:end="1:66">message</name></name>;</package>

<class pos:start="3:1" pos:end="9:1"><specifier pos:start="3:1" pos:end="3:6">public</specifier> class <name pos:start="3:14" pos:end="3:37">SetTargetAltitudeMessage</name> <super_list pos:start="3:39" pos:end="3:61"><extends pos:start="3:39" pos:end="3:61">extends <super pos:start="3:47" pos:end="3:61"><name pos:start="3:47" pos:end="3:61">AbstractMessage</name></super></extends></super_list> <block pos:start="3:63" pos:end="9:1">{
    <decl_stmt pos:start="4:5" pos:end="4:33"><decl pos:start="4:5" pos:end="4:32"><type pos:start="4:5" pos:end="4:23"><specifier pos:start="4:5" pos:end="4:10">public</specifier> <specifier pos:start="4:12" pos:end="4:16">final</specifier> <name pos:start="4:18" pos:end="4:23">double</name></type> <name pos:start="4:25" pos:end="4:32">altitude</name></decl>;</decl_stmt>

    <constructor pos:start="6:5" pos:end="8:5"><specifier pos:start="6:5" pos:end="6:10">public</specifier> <name pos:start="6:12" pos:end="6:35">SetTargetAltitudeMessage</name><parameter_list pos:start="6:36" pos:end="6:52">(<parameter pos:start="6:37" pos:end="6:51"><decl pos:start="6:37" pos:end="6:51"><type pos:start="6:37" pos:end="6:42"><name pos:start="6:37" pos:end="6:42">double</name></type> <name pos:start="6:44" pos:end="6:51">altitude</name></decl></parameter>)</parameter_list> <block pos:start="6:54" pos:end="8:5">{<block_content pos:start="7:9" pos:end="7:33">
        <expr_stmt pos:start="7:9" pos:end="7:33"><expr pos:start="7:9" pos:end="7:32"><name pos:start="7:9" pos:end="7:21"><name pos:start="7:9" pos:end="7:12">this</name><operator pos:start="7:13" pos:end="7:13">.</operator><name pos:start="7:14" pos:end="7:21">altitude</name></name> <operator pos:start="7:23" pos:end="7:23">=</operator> <name pos:start="7:25" pos:end="7:32">altitude</name></expr>;</expr_stmt>
    </block_content>}</block></constructor>
}</block></class>
</unit>
